redistributor.py
redistributor-1.0.0.dist-info/METADATA
redistributor-1.0.0.dist-info/WHEEL
redistributor-1.0.0.dist-info/top_level.txt
redistributor-1.0.0.dist-info/RECORD
