Metadata-Version: 2.1
Name: redistributor
Version: 1.0.0
Summary: A tool for automatic transformation of empirical data distributions
Author: Pavol Harar
Author-email: pavol.harar@gmail.com
License: MIT
Project-URL: Source, https://github.com/paloha/redistributor
Project-URL: Documentation, https://github.com/paloha/redistributor/raw/master/docs/redistributor.pdf
Project-URL: Publication, https://arxiv.org/abs/2210.14219
Project-URL: Issue tracker, https://github.com/paloha/redistributor/issues
Keywords: distribution transformation
Platform: any
Requires-Python: >3.6
Requires-Dist: numpy >=1.14.5
Requires-Dist: scipy >=1.1.0
Requires-Dist: scikit-learn >=0.19.1
Requires-Dist: psutil >=5.4.6
Provides-Extra: dev
Requires-Dist: pdoc3 ; extra == 'dev'
Requires-Dist: pyflakes ; extra == 'dev'
Requires-Dist: jupyter ; extra == 'dev'
Requires-Dist: pytest ; extra == 'dev'
